README.rst
setup.py
eetv/__init__.py
eetv/cli.py
eetv/eetv.py
eetv/keys.py
eetv.egg-info/PKG-INFO
eetv.egg-info/SOURCES.txt
eetv.egg-info/dependency_links.txt
eetv.egg-info/entry_points.txt
eetv.egg-info/requires.txt
eetv.egg-info/top_level.txt