Metadata-Version: 1.0
Name: eetv
Version: 0.0.3
Summary: Python bindings for the EETV appliance
Home-page: https://github.com/kevjs1982/python-eetv
Author: Kev Swindells
Author-email: kjs@kjs1982.me.uk
License: GPL3
Platform: UNKNOWN
